felupe/__about__.py
felupe/__init__.py
felupe/assembly/__init__.py
felupe/assembly/_axi.py
felupe/assembly/_cartesian.py
felupe/assembly/_integral.py
felupe/assembly/expression/__init__.py
felupe/assembly/expression/_basis.py
felupe/assembly/expression/_bilinear.py
felupe/assembly/expression/_decorator.py
felupe/assembly/expression/_expression.py
felupe/assembly/expression/_linear.py
felupe/assembly/expression/_mixed.py
felupe/constitution/__init__.py
felupe/constitution/_base.py
felupe/constitution/_kinematics.py
felupe/constitution/_material.py
felupe/constitution/_mixed.py
felupe/constitution/_view.py
felupe/constitution/hyperelasticity/__init__.py
felupe/constitution/hyperelasticity/_neo_hooke_compressible.py
felupe/constitution/hyperelasticity/_neo_hooke_nearly_incompressible.py
felupe/constitution/hyperelasticity/_ogden_roxburgh.py
felupe/constitution/hyperelasticity/_volumetric.py
felupe/constitution/jax/__init__.py
felupe/constitution/jax/_helpers.py
felupe/constitution/jax/_hyperelastic.py
felupe/constitution/jax/_material.py
felupe/constitution/jax/_total_lagrange.py
felupe/constitution/jax/_updated_lagrange.py
felupe/constitution/jax/models/__init__.py
felupe/constitution/jax/models/hyperelastic/__init__.py
felupe/constitution/jax/models/hyperelastic/_blatz_ko.py
felupe/constitution/jax/models/hyperelastic/_extended_tube.py
felupe/constitution/jax/models/hyperelastic/_miehe_goektepe_lulei.py
felupe/constitution/jax/models/hyperelastic/_mooney_rivlin.py
felupe/constitution/jax/models/hyperelastic/_neo_hooke.py
felupe/constitution/jax/models/hyperelastic/_storakers.py
felupe/constitution/jax/models/hyperelastic/_third_order_deformation.py
felupe/constitution/jax/models/hyperelastic/_van_der_waals.py
felupe/constitution/jax/models/hyperelastic/_yeoh.py
felupe/constitution/jax/models/hyperelastic/microsphere/__init__.py
felupe/constitution/jax/models/hyperelastic/microsphere/_chain.py
felupe-9.5.0.dist-info/licenses/LICENSE
felupe-9.5.0.dist-info/METADATA
felupe-9.5.0.dist-info/WHEEL
felupe-9.5.0.dist-info/top_level.txt
felupe-9.5.0.dist-info/RECORD
