Metadata-Version: 2.4
Name: felupe
Version: 9.5.0
Summary: Finite Element Analysis
Author-email: Andreas Dutzler <a.dutzler@gmail.com>
License-Expression: GPL-3.0-or-later
Project-URL: Homepage, https://felupe.readthedocs.io/en/latest
Project-URL: Documentation, https://felupe.readthedocs.io/en/latest
Project-URL: Repository, https://github.com/adtzlr/felupe
Project-URL: Issues, https://github.com/adtzlr/felupe/issues
Project-URL: Changelog, https://github.com/adtzlr/felupe/blob/main/CHANGELOG.md
Keywords: computational-mechanics,fea,fem,finite-elements,finite-elements-analysis,finite-elements-methods,hyperelasticity,partial-differential-equations,pde,python,scientific-computing,solid-mechanics-codes
Classifier: Development Status :: 5 - Production/Stable
Classifier: Programming Language :: Python
Classifier: Intended Audience :: Science/Research
Classifier: Operating System :: OS Independent
Classifier: Programming Language :: Python
Classifier: Programming Language :: Python :: 3
Classifier: Programming Language :: Python :: 3.9
Classifier: Programming Language :: Python :: 3.10
Classifier: Programming Language :: Python :: 3.11
Classifier: Programming Language :: Python :: 3.12
Classifier: Programming Language :: Python :: 3.13
Classifier: Topic :: Scientific/Engineering
Classifier: Topic :: Scientific/Engineering :: Mathematics
Classifier: Topic :: Utilities
Requires-Python: >=3.9
License-File: LICENSE
Requires-Dist: numpy
Requires-Dist: scipy
Provides-Extra: docs
Requires-Dist: pydata-sphinx-theme; extra == "docs"
Requires-Dist: sphinx-autoapi; extra == "docs"
Requires-Dist: sphinx-inline-tabs; extra == "docs"
Requires-Dist: sphinx-copybutton; extra == "docs"
Requires-Dist: sphinx-design; extra == "docs"
Requires-Dist: sphinx-gallery; extra == "docs"
Requires-Dist: pypandoc; extra == "docs"
Provides-Extra: autodiff
Requires-Dist: tensortrax; extra == "autodiff"
Requires-Dist: jax; extra == "autodiff"
Provides-Extra: examples
Requires-Dist: contique; extra == "examples"
Requires-Dist: imageio; extra == "examples"
Requires-Dist: pypardiso; extra == "examples"
Requires-Dist: torch; extra == "examples"
Provides-Extra: io
Requires-Dist: h5py; extra == "io"
Requires-Dist: meshio; extra == "io"
Provides-Extra: parallel
Requires-Dist: einsumt; extra == "parallel"
Provides-Extra: progress
Requires-Dist: tqdm; extra == "progress"
Provides-Extra: plot
Requires-Dist: matplotlib; extra == "plot"
Provides-Extra: view
Requires-Dist: pyvista[jupyter]; extra == "view"
Provides-Extra: all
Requires-Dist: felupe[autodiff,io,parallel,plot,progress,view]; extra == "all"
Dynamic: license-file
